budgetcb/__init__.py
budgetcb/base.py
budgetcb/constrained_cb.py
budgetcb/constrained_mab.py
budgetcb/helper.py
budgetcb/main.py
budgetcb/py.typed
budgetcb/replay.py
budgetcb/__pycache__/__init__.cpython-39.pyc
budgetcb/__pycache__/base.cpython-39.pyc
budgetcb/__pycache__/constrained_cb.cpython-39.pyc
budgetcb/__pycache__/constrained_mab.cpython-39.pyc
budgetcb/__pycache__/helper.cpython-39.pyc
budgetcb/__pycache__/replay.cpython-39.pyc
budgetcb/budget_constrained_CB.egg-info/PKG-INFO
budgetcb/budget_constrained_CB.egg-info/SOURCES.txt
budgetcb/budget_constrained_CB.egg-info/dependency_links.txt
budgetcb/budget_constrained_CB.egg-info/requires.txt
budgetcb/budget_constrained_CB.egg-info/top_level.txt
budget_constrained_CB-0.0.0.dist-info/LICENSE
budget_constrained_CB-0.0.0.dist-info/METADATA
budget_constrained_CB-0.0.0.dist-info/WHEEL
budget_constrained_CB-0.0.0.dist-info/top_level.txt
budget_constrained_CB-0.0.0.dist-info/RECORD
